{
  "outcome": "SUCCESS",
  "usage": {
    "tokensInput": 410,
    "tokensOutput": 674,
    "tokensTotal": 1084,
    "totalReasoningTokens": 512
  },
  "badResponses": 0,
  "verificationAttempts": 1,
  "resolutionAttempts": 1,
  "softFailedResolutions": 0,
  "hardFailedResolutions": 0,
  "responsesWithAssume": 0,
  "responsesWithExpect": 0,
  "experimentTimings": {
    "events": {
      "Overall Experiment": {
        "startTimeMs": 1780673906254,
        "endTimeMs": 1780673949102,
        "durationMs": 42848
      },
      "Iteration #1": {
        "startTimeMs": 1780673906261,
        "endTimeMs": 1780673949102,
        "durationMs": 42841
      }
    }
  }
}